{"createdAt":"2025-06-06T16:04:34.605Z","updatedAt":"2025-06-16T12:05:21.000Z","id":"lntOAKZTu2LScSxb","name":"0706_Monaco2","active":false,"nodes":[{"parameters":{},"id":"2fd580dc-186f-49c1-8040-e4c2f5f12c63","name":"When clicking ‘Test workflow’","type":"n8n-nodes-base.manualTrigger","typeVersion":1,"position":[1360,380]},{"parameters":{"documentId":{"__rl":true,"value":"1n8NiLd-gLUBiPeNH8PwfRpTCqLSf2pZ7SaLmXFLYKyQ","mode":"list","cachedResultName":"Planilha HD - Monaco Com Pontos","cachedResultUrl":"https://docs.google.com/spreadsheets/d/1n8NiLd-gLUBiPeNH8PwfRpTCqLSf2pZ7SaLmXFLYKyQ/edit?usp=drivesdk"},"sheetName":{"__rl":true,"value":"gid=0","mode":"list","cachedResultName":"pg1","cachedResultUrl":"https://docs.google.com/spreadsheets/d/1n8NiLd-gLUBiPeNH8PwfRpTCqLSf2pZ7SaLmXFLYKyQ/edit#gid=0"},"options":{}},"id":"844f6520-365f-4ada-b1a4-2395dbd86a43","name":"Google Sheets","type":"n8n-nodes-base.googleSheets","typeVersion":4.5,"position":[1600,380],"credentials":{"googleSheetsOAuth2Api":{"id":"W50qARSfHJAKIrXR","name":"Google Sheets account"}}},{"parameters":{"options":{}},"id":"a0a1d177-08eb-41c4-b377-5a1a5fd2baa2","name":"Loop Over Items","type":"n8n-nodes-base.splitInBatches","typeVersion":3,"position":[1880,240]},{"parameters":{},"id":"586393a4-92ff-4290-bd6c-855a99f14e75","name":"Replace Me","type":"n8n-nodes-base.noOp","typeVersion":1,"position":[2920,380]},{"parameters":{"operation":"update","documentId":{"__rl":true,"value":"1n8NiLd-gLUBiPeNH8PwfRpTCqLSf2pZ7SaLmXFLYKyQ","mode":"list","cachedResultName":"Planilha HD - Monaco Com Pontos","cachedResultUrl":"https://docs.google.com/spreadsheets/d/1n8NiLd-gLUBiPeNH8PwfRpTCqLSf2pZ7SaLmXFLYKyQ/edit?usp=drivesdk"},"sheetName":{"__rl":true,"value":"gid=0","mode":"list","cachedResultName":"pg1","cachedResultUrl":"https://docs.google.com/spreadsheets/d/1jk-yWMnM96Xx22dIVsG8kPpyuCiHLsj3QCVB3P9K884/edit#gid=0"},"columns":{"mappingMode":"defineBelow","value":{"row_number":"={{ $('Google Sheets').item.json.row_number }}","Enviado":"SIM","Saída":"=+551151989942"},"matchingColumns":["row_number"],"schema":[{"id":"Nome","displayName":"Nome","required":false,"defaultMatch":false,"display":true,"type":"string","canBeUsedToMatch":true,"removed":true},{"id":"email","displayName":"email","required":false,"defaultMatch":false,"display":true,"type":"string","canBeUsedToMatch":true,"removed":true},{"id":"Telefone","displayName":"Telefone","required":false,"defaultMatch":false,"display":true,"type":"string","canBeUsedToMatch":true,"removed":true},{"id":"CPF","displayName":"CPF","required":false,"defaultMatch":false,"display":true,"type":"string","canBeUsedToMatch":true,"removed":true},{"id":"Existe","displayName":"Existe","required":false,"defaultMatch":false,"display":true,"type":"string","canBeUsedToMatch":true,"removed":true},{"id":"Enviado","displayName":"Enviado","required":false,"defaultMatch":false,"display":true,"type":"string","canBeUsedToMatch":true},{"id":"Saída","displayName":"Saída","required":false,"defaultMatch":false,"display":true,"type":"string","canBeUsedToMatch":true},{"id":"row_number","displayName":"row_number","required":false,"defaultMatch":false,"display":true,"type":"string","canBeUsedToMatch":true,"readOnly":true,"removed":false}]},"options":{}},"id":"82bfb00e-a22f-46ba-9718-394cefa42862","name":"Google Sheets1","type":"n8n-nodes-base.googleSheets","typeVersion":4.5,"position":[2700,100],"credentials":{"googleSheetsOAuth2Api":{"id":"W50qARSfHJAKIrXR","name":"Google Sheets account"}}},{"parameters":{"conditions":{"options":{"caseSensitive":true,"leftValue":"","typeValidation":"strict","version":2},"conditions":[{"id":"00fe3841-bebd-4679-91b3-f37d994eba91","leftValue":"={{ $('Google Sheets').item.json.Enviado }}","rightValue":"","operator":{"type":"string","operation":"notEmpty","singleValue":true}},{"id":"3b33695b-8df7-4e6a-bd5f-a7428399c7cd","leftValue":"={{ $('Google Sheets').item.json.Existe }}","rightValue":"NÃO","operator":{"type":"string","operation":"equals","name":"filter.operator.equals"}}],"combinator":"or"},"options":{}},"id":"3be774a0-fbc6-43b7-ac56-ebc99a4e5d51","name":"If","type":"n8n-nodes-base.if","typeVersion":2.2,"position":[2100,260]},{"parameters":{"amount":"=1"},"id":"2bffbd89-83de-4a2f-bc91-7c2f60dde975","name":"Wait1","type":"n8n-nodes-base.wait","typeVersion":1.1,"position":[2520,100],"webhookId":"4c1f32ed-1dc6-4e81-8d11-388783adca91"},{"parameters":{"method":"POST","url":"=https://graph.facebook.com/v22.0/576678365532139/messages","authentication":"predefinedCredentialType","nodeCredentialType":"whatsAppApi","sendBody":true,"specifyBody":"json","jsonBody":"={\n    \"messaging_product\": \"whatsapp\",\n    \"recipient_type\": \"individual\",\n    \"to\": \"+55{{ $('Google Sheets').item.json.Telefone }}\",\n    \"type\": \"template\",\n    \"template\": {\n        \"name\": \"monaco2_slide1\",\n        \"language\": {\n            \"code\": \"pt_BR\"\n        },\n        \"components\": [\n            {\n                \"type\": \"header\",\n                \"parameters\": [\n                    {\n                        \"type\": \"image\",\n                        \"image\": {\n                            \"link\": \"https://mobilevet.blob.core.windows.net/arquivos/monaco-0706.jpg\"\n                        }\n                    }\n                ]\n            },\n            {\n                \"type\": \"body\",\n                \"parameters\": [\n                    {\n                        \"type\": \"text\",\n                        \"text\": \"{{ $('Google Sheets').item.json.Nome }}\"\n                    }\n                ]\n\n            }\n        ]\n    }\n}","options":{}},"id":"d52dd04a-8505-4959-a59b-f1f58badd51d","name":"Registrar","type":"n8n-nodes-base.httpRequest","typeVersion":4.2,"position":[2340,100],"credentials":{"whatsAppApi":{"id":"l3nIWHvQlOpPbtAx","name":"WhatsApp account"}}},{"parameters":{"rule":{"interval":[{"triggerAtHour":9}]}},"type":"n8n-nodes-base.scheduleTrigger","typeVersion":1.2,"position":[1360,220],"id":"27a66c17-7027-485b-b470-ad87bcf5e60f","name":"Schedule Trigger1"}],"connections":{"When clicking ‘Test workflow’":{"main":[[{"node":"Google Sheets","type":"main","index":0}]]},"Google Sheets":{"main":[[{"node":"Loop Over Items","type":"main","index":0}]]},"Replace Me":{"main":[[{"node":"Loop Over Items","type":"main","index":0}]]},"Google Sheets1":{"main":[[{"node":"Replace Me","type":"main","index":0}]]},"Loop Over Items":{"main":[[],[{"node":"If","type":"main","index":0}]]},"If":{"main":[[{"node":"Loop Over Items","type":"main","index":0}],[{"node":"Registrar","type":"main","index":0}]]},"Wait1":{"main":[[{"node":"Google Sheets1","type":"main","index":0}]]},"Registrar":{"main":[[{"node":"Wait1","type":"main","index":0}]]},"Schedule Trigger1":{"main":[[]]}},"settings":{"executionOrder":"v1"},"staticData":{"node:Schedule Trigger1":{"recurrenceRules":[]}},"meta":{"templateCredsSetupCompleted":true},"pinData":{},"versionId":"f7ee9525-2e89-4546-9aaf-079bc5ccf98f","triggerCount":1,"tags":[]}