{"createdAt":"2025-06-16T13:12:25.976Z","updatedAt":"2025-07-19T18:39:24.000Z","id":"exfeRoq8qJ6D6Gcx","name":"Envio Whatsapp Não Oficial","active":true,"nodes":[{"parameters":{},"id":"2ecc1b18-fffa-4238-972f-5bb471251baa","name":"When clicking ‘Test workflow’","type":"n8n-nodes-base.manualTrigger","typeVersion":1,"position":[1280,380]},{"parameters":{"options":{}},"id":"d4ab959f-6c07-4e7a-8d9c-43fd3a5ced87","name":"Loop Over Items","type":"n8n-nodes-base.splitInBatches","typeVersion":3,"position":[2040,380]},{"parameters":{},"id":"2f241513-5093-45ac-857e-1287d7c24f38","name":"Replace Me","type":"n8n-nodes-base.noOp","typeVersion":1,"position":[4180,640]},{"parameters":{"conditions":{"options":{"caseSensitive":true,"leftValue":"","typeValidation":"strict","version":2},"conditions":[{"id":"00fe3841-bebd-4679-91b3-f37d994eba91","leftValue":"={{ $('Lista Envio').item.json.Enviado }}","rightValue":"","operator":{"type":"string","operation":"notEmpty","singleValue":true}},{"id":"3b33695b-8df7-4e6a-bd5f-a7428399c7cd","leftValue":"={{ $('Lista Envio').item.json.Existe }}","rightValue":"NÃO","operator":{"type":"string","operation":"equals","name":"filter.operator.equals"}}],"combinator":"or"},"options":{}},"id":"2ed53d90-c16b-4a53-9e6a-803ae64f48cc","name":"If","type":"n8n-nodes-base.if","typeVersion":2.2,"position":[2200,500]},{"parameters":{"workflowId":{"__rl":true,"value":"nhQGpKE186cx7aN7","mode":"list","cachedResultName":"SubFluxo Disparo WhatsApp"},"workflowInputs":{"mappingMode":"defineBelow","value":{"tipo":"={{ $('Parametros').item.json.tipo }}","instancia":"={{ $('Parametros').item.json.intancias[$('Personalizar Mensagem').item.json['Ultimo Disparo']] }}","telefone":"={{ $('Lista Envio').item.json.Telefone.toString() }}","url-video":"={{ $('Parametros').item.json.url_video }}","url-imagem":"={{ $('Parametros').item.json.url_imagem }}","mensagem":"={{ $('Personalizar Mensagem').item.json.mensagem_personalizada }}","link":"={{ $json.link_personalizado }}"},"matchingColumns":[],"schema":[{"id":"instancia","displayName":"instancia","required":false,"defaultMatch":false,"display":true,"canBeUsedToMatch":true,"type":"string"},{"id":"tipo","displayName":"tipo","required":false,"defaultMatch":false,"display":true,"canBeUsedToMatch":true,"type":"string"},{"id":"telefone","displayName":"telefone","required":false,"defaultMatch":false,"display":true,"canBeUsedToMatch":true,"type":"string"},{"id":"url-video","displayName":"url-video","required":false,"defaultMatch":false,"display":true,"canBeUsedToMatch":true,"removed":false},{"id":"url-imagem","displayName":"url-imagem","required":false,"defaultMatch":false,"display":true,"canBeUsedToMatch":true,"removed":false},{"id":"mensagem","displayName":"mensagem","required":false,"defaultMatch":false,"display":true,"canBeUsedToMatch":true,"type":"string","removed":false},{"id":"link","displayName":"link","required":false,"defaultMatch":false,"display":true,"canBeUsedToMatch":true,"type":"string"},{"id":"nome","displayName":"nome","required":false,"defaultMatch":false,"display":true,"canBeUsedToMatch":true,"type":"string","removed":true},{"id":"pontos","displayName":"pontos","required":false,"defaultMatch":false,"display":true,"canBeUsedToMatch":true,"type":"string","removed":true},{"id":"extra-1","displayName":"extra-1","required":false,"defaultMatch":false,"display":true,"canBeUsedToMatch":true,"type":"string","removed":true},{"id":"extra-2","displayName":"extra-2","required":false,"defaultMatch":false,"display":true,"canBeUsedToMatch":true,"type":"string","removed":true}],"attemptToConvertTypes":false,"convertFieldsToString":true},"mode":"each","options":{}},"type":"n8n-nodes-base.executeWorkflow","typeVersion":1.2,"position":[3680,420],"id":"9604d270-f258-4fe6-948c-c712499cba38","name":"Execute Workflow"},{"parameters":{"workflowId":{"__rl":true,"value":"YJnP4hiWT0obkY2k","mode":"list","cachedResultName":"Balanceador Disparos Whatsapp"},"workflowInputs":{"mappingMode":"defineBelow","value":{"saida":"={{ $json['Saída'] }}","lista_instancia":"={{ $('Parametros').item.json.intancias }}","ultimo_disparo":"={{ $('Configuracoes').item.json['Ultimo Disparo'] }}"},"matchingColumns":[],"schema":[{"id":"saida","displayName":"saida","required":false,"defaultMatch":false,"display":true,"canBeUsedToMatch":true,"type":"string"},{"id":"lista_instancia","displayName":"lista_instancia","required":false,"defaultMatch":false,"display":true,"canBeUsedToMatch":true,"type":"array"},{"id":"ultimo_disparo","displayName":"ultimo_disparo","required":false,"defaultMatch":false,"display":true,"canBeUsedToMatch":true,"type":"number"}],"attemptToConvertTypes":false,"convertFieldsToString":true},"options":{}},"type":"n8n-nodes-base.executeWorkflow","typeVersion":1.2,"position":[2880,420],"id":"e27e9e00-4c96-464c-a70b-634ecadcbd6a","name":"Balanceador"},{"parameters":{"documentId":{"__rl":true,"value":"1NqsAnjlXXb9hwOtT0J8LJ-sFg8mEl_1iiljlvglWYfI","mode":"list","cachedResultName":"Configurações Disparo Whatsapp","cachedResultUrl":"https://docs.google.com/spreadsheets/d/1NqsAnjlXXb9hwOtT0J8LJ-sFg8mEl_1iiljlvglWYfI/edit?usp=drivesdk"},"sheetName":{"__rl":true,"value":"gid=0","mode":"list","cachedResultName":"pg1","cachedResultUrl":"https://docs.google.com/spreadsheets/d/1NqsAnjlXXb9hwOtT0J8LJ-sFg8mEl_1iiljlvglWYfI/edit#gid=0"},"options":{}},"id":"5861b26d-0d5a-4382-b868-228e3806edd9","name":"Configuracoes","type":"n8n-nodes-base.googleSheets","typeVersion":4.5,"position":[1460,380],"credentials":{"googleSheetsOAuth2Api":{"id":"W50qARSfHJAKIrXR","name":"Google Sheets account"}}},{"parameters":{"operation":"update","documentId":{"__rl":true,"value":"1mi6aBgQ7F6zx1CAeaqC59VlkeGJRAWw73dXgJzz_XtU","mode":"list","cachedResultName":"Lista Registro Automático","cachedResultUrl":"https://docs.google.com/spreadsheets/d/1mi6aBgQ7F6zx1CAeaqC59VlkeGJRAWw73dXgJzz_XtU/edit?usp=drivesdk"},"sheetName":{"__rl":true,"value":"gid=0","mode":"list","cachedResultName":"pg1","cachedResultUrl":"https://docs.google.com/spreadsheets/d/1jk-yWMnM96Xx22dIVsG8kPpyuCiHLsj3QCVB3P9K884/edit#gid=0"},"columns":{"mappingMode":"defineBelow","value":{"row_number":"={{ $('Lista Envio').item.json.row_number }}","Enviado":"SIM","Saída":"={{ $('Parametros').item.json.intancias[$('Personalizar Mensagem').item.json['Ultimo Disparo']] }}"},"matchingColumns":["row_number"],"schema":[{"id":"Nome","displayName":"Nome","required":false,"defaultMatch":false,"display":true,"type":"string","canBeUsedToMatch":true,"removed":true},{"id":"email","displayName":"email","required":false,"defaultMatch":false,"display":true,"type":"string","canBeUsedToMatch":true,"removed":true},{"id":"Telefone","displayName":"Telefone","required":false,"defaultMatch":false,"display":true,"type":"string","canBeUsedToMatch":true,"removed":true},{"id":"CPF","displayName":"CPF","required":false,"defaultMatch":false,"display":true,"type":"string","canBeUsedToMatch":true,"removed":true},{"id":"Existe","displayName":"Existe","required":false,"defaultMatch":false,"display":true,"type":"string","canBeUsedToMatch":true,"removed":true},{"id":"Enviado","displayName":"Enviado","required":false,"defaultMatch":false,"display":true,"type":"string","canBeUsedToMatch":true},{"id":"Saída","displayName":"Saída","required":false,"defaultMatch":false,"display":true,"type":"string","canBeUsedToMatch":true},{"id":"row_number","displayName":"row_number","required":false,"defaultMatch":false,"display":true,"type":"string","canBeUsedToMatch":true,"readOnly":true,"removed":false}],"attemptToConvertTypes":false,"convertFieldsToString":false},"options":{}},"id":"cd509f74-9085-4e09-a27e-685ffc96e74d","name":"Atualiza Envio","type":"n8n-nodes-base.googleSheets","typeVersion":4.5,"position":[3900,420],"credentials":{"googleSheetsOAuth2Api":{"id":"W50qARSfHJAKIrXR","name":"Google Sheets account"}}},{"parameters":{"assignments":{"assignments":[{"id":"8e8ac38b-df84-4953-b5df-5e08f8f3c30a","name":"intancias","value":"={{ $json.Instancias.split(',') }}","type":"array"},{"id":"320ae9bc-602d-4899-925a-ac2f7150c9ce","name":"mensagem","value":"={{ $json.Texto }}","type":"string"},{"id":"6db75a9f-bb92-4a46-b1a0-5787bee07aaf","name":"url_video","value":"={{ $json['Url Video'] }}","type":"string"},{"id":"7e3f35af-3710-4251-b2a2-c1e23dd8d568","name":"url_imagem","value":"={{ $json['Url Imagem'] }}","type":"string"},{"id":"0ec1ef3d-4795-4541-918d-6c439d3767ed","name":"texto_link","value":"={{ $json['Texto Link'] }}","type":"string"},{"id":"bfd5f9d2-911d-449b-9128-d7e01a9cebc0","name":"tipo","value":"={{ $json.Tipo }}","type":"string"}]},"options":{}},"type":"n8n-nodes-base.set","typeVersion":3.4,"position":[1640,380],"id":"de1e9a82-558d-4f67-839a-f82f5230193d","name":"Parametros"},{"parameters":{"operation":"update","documentId":{"__rl":true,"value":"1NqsAnjlXXb9hwOtT0J8LJ-sFg8mEl_1iiljlvglWYfI","mode":"list","cachedResultName":"Configurações Disparo Whatsapp","cachedResultUrl":"https://docs.google.com/spreadsheets/d/1NqsAnjlXXb9hwOtT0J8LJ-sFg8mEl_1iiljlvglWYfI/edit?usp=drivesdk"},"sheetName":{"__rl":true,"value":"gid=0","mode":"list","cachedResultName":"pg1","cachedResultUrl":"https://docs.google.com/spreadsheets/d/1NqsAnjlXXb9hwOtT0J8LJ-sFg8mEl_1iiljlvglWYfI/edit#gid=0"},"columns":{"mappingMode":"defineBelow","value":{"row_number":"={{ $('Configuracoes').item.json.row_number }}","Ultimo Disparo":"={{ $json.result }}"},"matchingColumns":["row_number"],"schema":[{"id":"Ultimo Disparo","displayName":"Ultimo Disparo","required":false,"defaultMatch":false,"display":true,"type":"string","canBeUsedToMatch":true,"removed":false},{"id":"row_number","displayName":"row_number","required":false,"defaultMatch":false,"display":true,"type":"string","canBeUsedToMatch":true,"readOnly":true,"removed":false}],"attemptToConvertTypes":false,"convertFieldsToString":false},"options":{}},"id":"9a5bde74-4c8f-4c13-9fd2-2d30a4f0ba7f","name":"Atualizar Disparo","type":"n8n-nodes-base.googleSheets","typeVersion":4.5,"position":[3080,420],"credentials":{"googleSheetsOAuth2Api":{"id":"W50qARSfHJAKIrXR","name":"Google Sheets account"}}},{"parameters":{"assignments":{"assignments":[{"id":"f5da3c66-332f-43d3-9d87-2c109054843d","name":"mensagem_personalizada","value":"={{ $('Parametros').item.json.mensagem.replaceAll('[NOME]',$('If').item.json.Nome).replaceAll('[PONTOS]', $('If').item.json.Pontos).replaceAll('[PARAMETROLINK]',$('If').item.json.Parametro) }}","type":"string"}]},"includeOtherFields":true,"options":{}},"type":"n8n-nodes-base.set","typeVersion":3.4,"position":[3280,420],"id":"3ac46927-1533-40dd-ac27-51164bc2d89e","name":"Personalizar Mensagem"},{"parameters":{"documentId":{"__rl":true,"value":"1mi6aBgQ7F6zx1CAeaqC59VlkeGJRAWw73dXgJzz_XtU","mode":"list","cachedResultName":"Lista Registro Automático","cachedResultUrl":"https://docs.google.com/spreadsheets/d/1mi6aBgQ7F6zx1CAeaqC59VlkeGJRAWw73dXgJzz_XtU/edit?usp=drivesdk"},"sheetName":{"__rl":true,"value":"gid=0","mode":"list","cachedResultName":"pg1","cachedResultUrl":"https://docs.google.com/spreadsheets/d/1mi6aBgQ7F6zx1CAeaqC59VlkeGJRAWw73dXgJzz_XtU/edit#gid=0"},"options":{}},"id":"687cc9d9-4818-4e69-8a90-e9fc9fa171e5","name":"Lista Envio","type":"n8n-nodes-base.googleSheets","typeVersion":4.5,"position":[1820,380],"credentials":{"googleSheetsOAuth2Api":{"id":"W50qARSfHJAKIrXR","name":"Google Sheets account"}}},{"parameters":{"rule":{"interval":[{"triggerAtHour":18},{"triggerAtHour":8,"triggerAtMinute":30}]}},"type":"n8n-nodes-base.scheduleTrigger","typeVersion":1.2,"position":[1280,200],"id":"7ba8daa3-590e-4eb2-bd1d-5a2bdc800d67","name":"Schedule Trigger"},{"parameters":{"assignments":{"assignments":[{"id":"3b138cd7-894c-4249-bb59-401229cc22cb","name":"link_personalizado","value":"={{ $('Parametros').item.json.texto_link.replaceAll('[PARAMETROLINK]',$('If').item.json.Parametro) }}","type":"string"}]},"options":{}},"type":"n8n-nodes-base.set","typeVersion":3.4,"position":[3480,420],"id":"b7158ed0-596d-4a33-9915-8eafabf2ad67","name":"Personalizar Link"},{"parameters":{"workflowId":{"__rl":true,"value":"Ec83xKzUmkGF1Mr2","mode":"list","cachedResultName":"Existe Whatsapp"},"workflowInputs":{"mappingMode":"defineBelow","value":{"telefone":"={{ $json.Telefone }}"},"matchingColumns":["telefone"],"schema":[{"id":"telefone","displayName":"telefone","required":false,"defaultMatch":false,"display":true,"canBeUsedToMatch":true,"removed":false}],"attemptToConvertTypes":false,"convertFieldsToString":true},"options":{}},"type":"n8n-nodes-base.executeWorkflow","typeVersion":1.2,"position":[2420,520],"id":"732b2252-9d05-462d-b9b8-b33a66b7296d","name":"Execute Workflow1"},{"parameters":{"conditions":{"options":{"caseSensitive":true,"leftValue":"","typeValidation":"strict","version":2},"conditions":[{"id":"79965ecf-5f80-4d5d-b503-a78e4cb69902","leftValue":"={{ $json.response }}","rightValue":"true","operator":{"type":"string","operation":"equals"}}],"combinator":"and"},"options":{}},"type":"n8n-nodes-base.if","typeVersion":2.2,"position":[2640,520],"id":"d47ae0ad-3974-4975-beec-d501743cca15","name":"If1"},{"parameters":{"operation":"update","documentId":{"__rl":true,"value":"1mi6aBgQ7F6zx1CAeaqC59VlkeGJRAWw73dXgJzz_XtU","mode":"list","cachedResultName":"Lista Registro Automático","cachedResultUrl":"https://docs.google.com/spreadsheets/d/1mi6aBgQ7F6zx1CAeaqC59VlkeGJRAWw73dXgJzz_XtU/edit?usp=drivesdk"},"sheetName":{"__rl":true,"value":"gid=0","mode":"list","cachedResultName":"pg1","cachedResultUrl":"https://docs.google.com/spreadsheets/d/1jk-yWMnM96Xx22dIVsG8kPpyuCiHLsj3QCVB3P9K884/edit#gid=0"},"columns":{"mappingMode":"defineBelow","value":{"row_number":"={{ $('Lista Envio').item.json.row_number }}","Enviado":"NÃO","Saída":"={{ $('Parametros').item.json.intancias[$('Configuracoes').item.json['Ultimo Disparo']] }}"},"matchingColumns":["row_number"],"schema":[{"id":"Nome","displayName":"Nome","required":false,"defaultMatch":false,"display":true,"type":"string","canBeUsedToMatch":true,"removed":true},{"id":"email","displayName":"email","required":false,"defaultMatch":false,"display":true,"type":"string","canBeUsedToMatch":true,"removed":true},{"id":"Telefone","displayName":"Telefone","required":false,"defaultMatch":false,"display":true,"type":"string","canBeUsedToMatch":true,"removed":true},{"id":"CPF","displayName":"CPF","required":false,"defaultMatch":false,"display":true,"type":"string","canBeUsedToMatch":true,"removed":true},{"id":"Existe","displayName":"Existe","required":false,"defaultMatch":false,"display":true,"type":"string","canBeUsedToMatch":true,"removed":true},{"id":"Enviado","displayName":"Enviado","required":false,"defaultMatch":false,"display":true,"type":"string","canBeUsedToMatch":true},{"id":"Saída","displayName":"Saída","required":false,"defaultMatch":false,"display":true,"type":"string","canBeUsedToMatch":true},{"id":"row_number","displayName":"row_number","required":false,"defaultMatch":false,"display":true,"type":"string","canBeUsedToMatch":true,"readOnly":true,"removed":false}],"attemptToConvertTypes":false,"convertFieldsToString":false},"options":{}},"id":"f857f5ff-1b15-4e2b-8a46-696389b660a5","name":"Atualiza Envio1","type":"n8n-nodes-base.googleSheets","typeVersion":4.5,"position":[2880,640],"credentials":{"googleSheetsOAuth2Api":{"id":"W50qARSfHJAKIrXR","name":"Google Sheets account"}}}],"connections":{"When clicking ‘Test workflow’":{"main":[[{"node":"Configuracoes","type":"main","index":0}]]},"Replace Me":{"main":[[{"node":"Loop Over Items","type":"main","index":0}]]},"Loop Over Items":{"main":[[],[{"node":"If","type":"main","index":0}]]},"If":{"main":[[{"node":"Loop Over Items","type":"main","index":0}],[{"node":"Execute Workflow1","type":"main","index":0}]]},"Execute Workflow":{"main":[[{"node":"Atualiza Envio","type":"main","index":0}]]},"Balanceador":{"main":[[{"node":"Atualizar Disparo","type":"main","index":0}]]},"Configuracoes":{"main":[[{"node":"Parametros","type":"main","index":0}]]},"Atualiza Envio":{"main":[[{"node":"Replace Me","type":"main","index":0}]]},"Parametros":{"main":[[{"node":"Lista Envio","type":"main","index":0}]]},"Atualizar Disparo":{"main":[[{"node":"Personalizar Mensagem","type":"main","index":0}]]},"Personalizar Mensagem":{"main":[[{"node":"Personalizar Link","type":"main","index":0}]]},"Lista Envio":{"main":[[{"node":"Loop Over Items","type":"main","index":0}]]},"Schedule Trigger":{"main":[[{"node":"Configuracoes","type":"main","index":0}]]},"Personalizar Link":{"main":[[{"node":"Execute Workflow","type":"main","index":0}]]},"Execute Workflow1":{"main":[[{"node":"If1","type":"main","index":0}]]},"If1":{"main":[[{"node":"Balanceador","type":"main","index":0}],[{"node":"Atualiza Envio1","type":"main","index":0}]]},"Atualiza Envio1":{"main":[[{"node":"Replace Me","type":"main","index":0}]]}},"settings":{"executionOrder":"v1"},"staticData":{"node:Schedule Trigger":{"recurrenceRules":[]}},"meta":{"templateCredsSetupCompleted":true},"pinData":{},"versionId":"1fc55ed3-4ff5-42ad-88e4-e981646e8ae0","triggerCount":1,"tags":[]}